MANIFEST.in
README.rst
setup.py
version.txt
libopenzwave/__init__.py
libopenzwave/_global.py
libopenzwave/_version.py
libopenzwave/build.py
libopenzwave/manager.py
libopenzwave/options.py
libopenzwave/tests/__init__.py
libopenzwave_cffi.egg-info/PKG-INFO
libopenzwave_cffi.egg-info/SOURCES.txt
libopenzwave_cffi.egg-info/dependency_links.txt
libopenzwave_cffi.egg-info/top_level.txt